Workbook
Name Slicer_Account1: #N/A

Sheet Charts of Accounts
A1: Accounts | C1: Sub Accounts | D1: Assets | E1: Financial Statement | F1: Individual Accounts | G1: Sub-Accounts
A2: Assets | C2: Current Assets | D2: Assets | E2: Balance Sheet | F2: Cash | G2: Current Assets
A3: Liabilities | C3: Fixed Assets | D3: Assets | E3: Balance Sheet | F3: Equity -Owais | G3: Equity
A4: Equity | C4: Current Liablilities | D4: Liabilities | E4: Balance Sheet | F4: Bank 1122 | G4: Current Assets
A5: Expenses | C5: Fixed Liablities | D5: Liabilities | E5: Balance Sheet | F5: Inventory | G5: Current Assets
A6: Revenue | C6: Equity | D6: Equity | E6: Balance Sheet | F6: Mr.Zubair | G6: Current Liablilities
C7: Expenses | D7: Expenses | E7: Income Statement | F7: Sales | G7: Revenue
C8: Revenue | D8: Revenue | E8: Income Statement | F8: Cost of Goods Sold | G8: Expenses
C9: Contra Revenue | D9: Contra Revenue | E9: Income Statement | F9: Kazim | G9: Current Assets
F10: Electricity | G10: Expenses
F11: Salary | G11: Expenses
F12: Taxes | G12: Expenses
F13: Govt | G13: Current Liablilities
F14: Shop | G14: Fixed Assets

Sheet Journal Entries
A1: Date | B1: Description | C1: Account | D1: Debit | E1: Credit | F1: Comment | I1: *Establish a business by Owais, investing Rs 1 million in Cash on 01-Jan-22
A2: 45658 | B2: Establish a business | C2: Cash | D2: 1000000
A3: 44562 | B3: Establish a business | C3: Equity -Owais | E3: 1000000 | I3: *Deposit Rs. 5 lac into Bank on 2 Jan 2022
A4: 44563 | B4: Bank Deposits | C4: Bank 1122 | D4: 500000
A5: 44563 | B5: Bank Deposits | C5: Cash | E5: 500000 | I5: *Purchase inventory of Rs 600,000 on credit from Mr.Zubair
A6: 44564 | B6: Purchased Inventory | C6: Inventory | D6: 600000
A7: 44564 | B7: Purchased Inventory | C7: Mr.Zubair | E7: 600000 | I7: *Purchase inventory of Rs 200,000 by paying through Cheque from Mr.Ahmed
A8: 44565 | B8: Purchased Inventory | C8: Inventory | D8: 200000
A9: 44565 | B9: Purchased Inventory | C9: Bank 1122 | E9: 200000 | I9: *Sold inventory for Rs 400,000 on Cash on 10th Jan 2022
A10: 44571 | B10: Sold inventory for Cash | C10: Cash | D10: 400000
A11: 44571 | B11: Sold inventory for Cash | C11: Sales | E11: 400000 | I11: *Sold inventory for Rs 300,000 on Credit to Mr.Kazim on 15 Jan 2022
A12: 44571 | B12: Adjust inventory agains COGs | C12: Cost of Goods Sold | D12: 300000
A13: 44571 | B13: Adjust inventory agains COGs | C13: Inventory | E13: 300000 | I13: *Paid electricity bills of Rs.15000
A14: 44576 | B14: Sold inventory on credit | C14: Kazim | D14: 300000
A15: 44576 | B15: Sold inventory on credit | C15: Sales | E15: 300000
A16: 44576 | B16: Adjust inventory agains COGs | C16: Cost of Goods Sold | D16: 150000
A17: 44576 | B17: Adjust inventory agains COGs | C17: Inventory | E17: 150000
A18: 44579 | B18: Paid Electricity | C18: Electricity | D18: 15000
A19: 44579 | B19: Paid Electricity | C19: Bank 1122 | E19: 15000
A20: 44591 | B20: Paid Salary | C20: Salary | D20: 100000
A21: 44591 | B21: Paid Salary | C21: Cash | E21: 100000
A22: 44594 | B22: Paid to Mr.Zubair | C22: Mr.Zubair | D22: 100000
A23: 44594 | B23: Paid to Mr.Zubair | C23: Cash | E23: 100000
A24: 44607 | B24: Received from Mr.Kazim | C24: Bank 1122 | D24: 150000
A25: 44607 | B25: Received from Mr.Kazim | C25: Kazim | E25: 150000
A26: 44650 | B26: Taxes Payable to Government | C26: Taxes | D26: 20250
A27: 44650 | B27: Taxes Payable to Government | C27: Govt | E27: 20250
A28: 44602 | B28: Purchased a shop | C28: Shop | D28: 100000
A29: 44602 | B29: Purchased a shop | C29: Cash | E29: 100000

Sheet Ledger
A2: =B4 -> Mr.Zubair | C2: =VLOOKUP(A2,'Charts of Accounts'!F:G,2,0) -> Current Liablilities
A3: Date | B3: Account | C3: Description | D3: Sum of Debit | E3: Sum of Credit | F3: Sum of Balance
A4: 44564 | B4: Mr.Zubair | C4: Purchased Inventory | E4: 600000 | F4: -600000
A5: 44594 | B5: Mr.Zubair | C5: Paid to Mr.Zubair | D5: 100000 | F5: 100000
A6: Grand Total | D6: 100000 | E6: 600000 | F6: -500000

Sheet Trial Balance
A2: Trial Balance
A3: Account | B3: Sum of Debit | C3: Sum of Credit | D3: Sum of Balance
A4: Bank 1122 | B4: 650000 | C4: 215000 | D4: 435000 | F4: =VLOOKUP(A4,'Charts of Accounts'!F:G,2,0) -> Current Assets | G4: =VLOOKUP(F4,'Charts of Accounts'!$C:$E,3,0) -> Balance Sheet
A5: Cash | B5: 1400000 | C5: 800000 | D5: 600000 | F5: =VLOOKUP(A5,'Charts of Accounts'!F:G,2,0) -> Current Assets | G5: =VLOOKUP(F5,'Charts of Accounts'!$C:$E,3,0) -> Balance Sheet
A6: Cost of Goods Sold | B6: 450000 | D6: 450000 | F6: =VLOOKUP(A6,'Charts of Accounts'!F:G,2,0) -> Expenses | G6: =VLOOKUP(F6,'Charts of Accounts'!$C:$E,3,0) -> Income Statement
A7: Electricity | B7: 15000 | D7: 15000 | F7: =VLOOKUP(A7,'Charts of Accounts'!F:G,2,0) -> Expenses | G7: =VLOOKUP(F7,'Charts of Accounts'!$C:$E,3,0) -> Income Statement
A8: Equity -Owais | C8: 1000000 | D8: -1000000 | F8: =VLOOKUP(A8,'Charts of Accounts'!F:G,2,0) -> Equity | G8: =VLOOKUP(F8,'Charts of Accounts'!$C:$E,3,0) -> Balance Sheet
A9: Inventory | B9: 800000 | C9: 450000 | D9: 350000 | F9: =VLOOKUP(A9,'Charts of Accounts'!F:G,2,0) -> Current Assets | G9: =VLOOKUP(F9,'Charts of Accounts'!$C:$E,3,0) -> Balance Sheet
A10: Kazim | B10: 300000 | C10: 150000 | D10: 150000 | F10: =VLOOKUP(A10,'Charts of Accounts'!F:G,2,0) -> Current Assets | G10: =VLOOKUP(F10,'Charts of Accounts'!$C:$E,3,0) -> Balance Sheet
A11: Mr.Zubair | B11: 100000 | C11: 600000 | D11: -500000 | F11: =VLOOKUP(A11,'Charts of Accounts'!F:G,2,0) -> Current Liablilities | G11: =VLOOKUP(F11,'Charts of Accounts'!$C:$E,3,0) -> Balance Sheet
A12: Salary | B12: 100000 | D12: 100000 | F12: =VLOOKUP(A12,'Charts of Accounts'!F:G,2,0) -> Expenses | G12: =VLOOKUP(F12,'Charts of Accounts'!$C:$E,3,0) -> Income Statement
A13: Sales | C13: 700000 | D13: -700000 | F13: =VLOOKUP(A13,'Charts of Accounts'!F:G,2,0) -> Revenue | G13: =VLOOKUP(F13,'Charts of Accounts'!$C:$E,3,0) -> Income Statement
A14: Taxes | B14: 20250 | D14: 20250 | F14: =VLOOKUP(A14,'Charts of Accounts'!F:G,2,0) -> Expenses | G14: =VLOOKUP(F14,'Charts of Accounts'!$C:$E,3,0) -> Income Statement
A15: Govt | C15: 20250 | D15: -20250 | F15: =VLOOKUP(A15,'Charts of Accounts'!F:G,2,0) -> Current Liablilities | G15: =VLOOKUP(F15,'Charts of Accounts'!$C:$E,3,0) -> Balance Sheet
A16: Shop | B16: 100000 | D16: 100000
A17: Grand Total | B17: 3935250 | C17: 3935250 | D17: 0

Sheet Income Statement
B2: Sofia Company PVT
B3: INCOME STATEMENT
B4: For the period of 1st March 2025
C6: Sales | G6: =VLOOKUP(C6,'Trial Balance'!$A$4:$D$13,4,0)*-1 -> 700000
C7: Cost of Goods Sold | G7: =VLOOKUP(C7,'Trial Balance'!$A$4:$D$13,4,0)*-1 -> -450000
C8: Gross Profit | G8: =G6+G7 -> 250000
C10: Operating Expenses
C12: Salary | F12: =VLOOKUP(C12,'Trial Balance'!$A$4:$D$13,4,0) -> 100000
C13: Electricity | F13: =VLOOKUP(C13,'Trial Balance'!$A$4:$D$13,4,0) -> 15000
C14: Total of Operating Expenses | G14: =F12+F13 -> 115000
C15: Operating Profit | G15: =G8-G14 -> 135000
C16: Taxes(15%) | G16: =G15*0.15 -> 20250
C17: Net Profit | G17: =G15-G16 -> 114750

Sheet Balance Sheet
B2: Sofia Company PVT
B3: Balance Sheet
B4: As on 31st March,2025
B6: Assets | G6: Liabilities and Equities
B8: Fixed Assets | G8: Liabilities
G9: Fixed Liabilities | K9: 0
B10: Shop | E10: =VLOOKUP(B10,'Trial Balance'!A4:D16,4,0) -> 100000
B11: Total of Fixed Assets | F11: =E10 -> 100000
G13: Current Liabilities
B15: Current Assets | H15: Mr.Zubair | J15: =VLOOKUP(H15,'Trial Balance'!A4:D16,4,0)*-1 -> 500000
H16: Govt | J16: =VLOOKUP(H16,'Trial Balance'!A5:D17,4,0)*-1 -> 20250
B17: Bank 1122 | E17: =VLOOKUP(B17,'Trial Balance'!A4:D16,4,0) -> 435000
B18: Cash | E18: =VLOOKUP(B18,'Trial Balance'!A5:D17,4,0) -> 600000 | G18: Total of Current Liabilities | K18: =J15+J16 -> 520250
B19: Inventory | E19: =VLOOKUP(B19,'Trial Balance'!A6:D18,4,0) -> 350000
B20: Kazim | E20: =VLOOKUP(B20,'Trial Balance'!A7:D19,4,0) -> 150000
B21: Total of Assets | F21: =SUM(E17:E20) -> 1535000 | G21: Equity
H22: Equity-Owais | J22: 1000000
H23: Retain Earning | J23: ='Income Statement'!G17 -> 114750
G24: Total of Equity | K24: =J22+J23 -> 1114750
B25: Total of Assets | F25: =F11+F21 -> 1635000 | K25: =K18+K24 -> 1635000
G26: Total of liabilities +Equity
